setup.cfg
setup.py
fito/__init__.py
fito/config.py
fito/global_config.py
fito/ioc.py
fito/operation_runner.py
fito/version_tracker.py
fito.egg-info/PKG-INFO
fito.egg-info/SOURCES.txt
fito.egg-info/dependency_links.txt
fito.egg-info/not-zip-safe
fito.egg-info/requires.txt
fito.egg-info/top_level.txt
fito/data_store/__init__.py
fito/data_store/base.py
fito/data_store/dict_ds.py
fito/data_store/file.py
fito/data_store/mongo.py
fito/data_store/pandas_ds.py
fito/data_store/refactor.py
fito/data_store/rehash_ui.py
fito/data_store/store_manager.py
fito/model/__init__.py
fito/model/model.py
fito/model/scikit_learn.py
fito/model/word2vec.py
fito/operations/__init__.py
fito/operations/decorate.py
fito/operations/operation.py
fito/operations/series.py
fito/specs/__init__.py
fito/specs/base.py
fito/specs/diff.py
fito/specs/fields.py
fito/specs/utils.py