Metadata-Version: 1.1
Name: fito
Version: 0.5.1
Summary: fito
Home-page: https://github.com/elsonidoq/fito
Author: Pablo Zivic
Author-email: elsonidoq@gmail.com
License: UNKNOWN
Download-URL: https://github.com/elsonidoq/fito/tarball/0.5.1
Platform: UNKNOWN
